hdfe/__init__.py
hdfe/groupby.py
hdfe/hdfe.py
hdfe/multicollinearity.py
hdfe-0.0.4.dist-info/LICENSE
hdfe-0.0.4.dist-info/METADATA
hdfe-0.0.4.dist-info/WHEEL
hdfe-0.0.4.dist-info/top_level.txt
hdfe-0.0.4.dist-info/RECORD
