Metadata-Version: 2.1
Name: hdfe
Version: 0.0.4
Summary: Econometric tools for working with panel data and fixed effects
Home-page: https://github.com/esantorella/hdfe/
Author: Elizabeth Santorella
Author-email: elizabeth.santorella@gmail.com
License: MIT
Platform: UNKNOWN
Classifier: Programming Language :: Python :: 3
Classifier: License :: OSI Approved :: MIT License
Classifier: Operating System :: OS Independent
Requires-Dist: numpy
Requires-Dist: pandas (>=0.25.0)
Requires-Dist: scipy
